sky_optimizer/__init__.py
sky_optimizer/factory.py
sky_optimizer/optimizer.py
sky_optimizer/py.typed
sky_optimizer/mixins/__init__.py
sky_optimizer/mixins/grad_mixin.py
sky_optimizer/mixins/metrics_mixin.py
sky_optimizer/mixins/state_mixin.py
sky_optimizer/mixins/step_mixin.py
sky_optimizer/utils/__init__.py
sky_optimizer/utils/agc.py
sky_optimizer-1.0.0.dist-info/licenses/LICENSE
sky_optimizer-1.0.0.dist-info/METADATA
sky_optimizer-1.0.0.dist-info/WHEEL
sky_optimizer-1.0.0.dist-info/top_level.txt
sky_optimizer-1.0.0.dist-info/RECORD
