Metadata-Version: 2.4
Name: sky-optimizer
Version: 1.0.0
Summary: Revolutionary Mathematical Optimization Algorithm combining cutting-edge techniques
Home-page: https://github.com/pro-creations/sky-optimizer
Author: Pro-Creations
Author-email: Pro-Creations <support@pro-creations.com>
Maintainer-email: Pro-Creations <support@pro-creations.com>
License: MIT License
Project-URL: Homepage, https://github.com/pro-creations/sky-optimizer
Project-URL: Bug Tracker, https://github.com/pro-creations/sky-optimizer/issues
Project-URL: Documentation, https://github.com/pro-creations/sky-optimizer/blob/main/README.md
Project-URL: Source Code, https://github.com/pro-creations/sky-optimizer
Project-URL: Changelog, https://github.com/pro-creations/sky-optimizer/blob/main/CHANGELOG.md
Keywords: optimizer,pytorch,machine-learning,deep-learning,optimization,riemannian-geometry,natural-gradients,quasi-newton,information-theory,meta-learning,bayesian-optimization,matrix-factorization,stochastic-differential-equations,trust-region,conjugate-gradients,mathematical-optimization,artificial-intelligence,neural-networks
Classifier: Development Status :: 5 - Production/Stable
Classifier: Intended Audience :: Developers
Classifier: Intended Audience :: Science/Research
Classifier: License :: OSI Approved :: MIT License
Classifier: Operating System :: OS Independent
Classifier: Programming Language :: Python :: 3
Classifier: Programming Language :: Python :: 3.8
Classifier: Programming Language :: Python :: 3.9
Classifier: Programming Language :: Python :: 3.10
Classifier: Programming Language :: Python :: 3.11
Classifier: Programming Language :: Python :: 3.12
Classifier: Topic :: Scientific/Engineering
Classifier: Topic :: Scientific/Engineering :: Artificial Intelligence
Classifier: Topic :: Scientific/Engineering :: Mathematics
Classifier: Topic :: Software Development :: Libraries :: Python Modules
Classifier: Typing :: Typed
Requires-Python: >=3.8
License-File: LICENSE
Requires-Dist: torch>=1.11.0
Requires-Dist: numpy>=1.19.0
Provides-Extra: advanced
Requires-Dist: scipy>=1.7.0; extra == "advanced"
Provides-Extra: dev
Requires-Dist: pytest>=6.0.0; extra == "dev"
Requires-Dist: pytest-cov>=2.10.0; extra == "dev"
Requires-Dist: black>=21.0.0; extra == "dev"
Requires-Dist: flake8>=3.8.0; extra == "dev"
Requires-Dist: mypy>=0.800; extra == "dev"
Requires-Dist: pre-commit>=2.10.0; extra == "dev"
Provides-Extra: benchmark
Requires-Dist: psutil>=5.8.0; extra == "benchmark"
Requires-Dist: matplotlib>=3.3.0; extra == "benchmark"
Provides-Extra: all
Requires-Dist: scipy>=1.7.0; extra == "all"
Requires-Dist: pytest>=6.0.0; extra == "all"
Requires-Dist: pytest-cov>=2.10.0; extra == "all"
Requires-Dist: black>=21.0.0; extra == "all"
Requires-Dist: flake8>=3.8.0; extra == "all"
Requires-Dist: mypy>=0.800; extra == "all"
Requires-Dist: pre-commit>=2.10.0; extra == "all"
Requires-Dist: psutil>=5.8.0; extra == "all"
Requires-Dist: matplotlib>=3.3.0; extra == "all"
Dynamic: author
Dynamic: home-page
Dynamic: license-file
Dynamic: requires-python
